MANIFEST.in
README.md
setup.py
mc_banyan.egg-info/PKG-INFO
mc_banyan.egg-info/SOURCES.txt
mc_banyan.egg-info/dependency_links.txt
mc_banyan.egg-info/requires.txt
mc_banyan.egg-info/top_level.txt
scripts/banyan
src/__init__.py
src/app.py
src/assert_util.py
src/banyan_opt.py
src/clear_deploy.py
src/config.py
src/debug.py
src/defaults.py
src/deploy.py
src/deploy_info.py
src/gate.py
src/get_code_with_tag.py
src/githelper.py
src/init_config.py
src/roles.py
src/util.py
src/auth_template/auth_db/defaults/main.yml.t
src/auth_template/auth_db/tasks/main.yml.t
src/auth_template/auth_db/vars/main.yml.t
src/auth_template/microservice_gate/tasks/main.yml.t
src/auth_template/microservice_gate/templates/login.conf.template.t
src/auth_template/microservice_gate/vars/main.yml.t
src/tools/__init__.py
src/tools/data_convert.py
src/tools/dicthelper.py
src/tools/file.py
src/tools/folder.py