Metadata-Version: 1.1
Name: mc-banyan
Version: 2.1.1
Summary: banyan is a tool to manage the deployment tasks for microservices.
Home-page: UNKNOWN
Author: Zongying Cao
Author-email: zongying.cao@dxc.com
License: Apache
Platform: UNKNOWN
Classifier: Development Status :: 4 - Beta
Classifier: Intended Audience :: Developers
Classifier: License :: OSI Approved :: Apache Software License
Classifier: Natural Language :: English
Classifier: Operating System :: OS Independent
Classifier: Programming Language :: Python :: 3
Classifier: Topic :: Software Development :: Libraries
